taum/__init__.py
taum/utils.py
taum-0.1.0.dist-info/METADATA
taum-0.1.0.dist-info/WHEEL
taum-0.1.0.dist-info/top_level.txt
taum-0.1.0.dist-info/RECORD
