Metadata-Version: 2.1
Name: taum
Version: 0.1.0
Summary: Pytorch Audio Models
Author-email: Dan Jacobellis <danjacobellis@utexas.edu>
Classifier: Programming Language :: Python :: 3
Classifier: Operating System :: OS Independent
Requires-Python: >=3.6
Requires-Dist: torch
Requires-Dist: torchaudio
